{
    "key": "group_5d1cf3cf6d1fd",
    "title": "Page - hreflang",
    "fields": [
        {
            "key": "field_5d1cf3de2aa2c",
            "label": "HREFLANG Tags",
            "name": "hreflang",
            "type": "repeater",
            "instructions": "Collection of \"hreflang\" links and language attributes to add into the page header",
            "required": 0,
            "conditional_logic": 0,
            "wrapper": {
                "width": "",
                "class": "",
                "id": ""
            },
            "collapsed": "",
            "min": 0,
            "max": 0,
            "layout": "block",
            "button_label": "Add Tag",
            "sub_fields": [
                {
                    "key": "field_5d1cf4912aa2d",
                    "label": "Link",
                    "name": "link",
                    "type": "url",
                    "instructions": "",
                    "required": 1,
                    "conditional_logic": 0,
                    "wrapper": {
                        "width": "65",
                        "class": "",
                        "id": ""
                    },
                    "default_value": "",
                    "placeholder": ""
                },
                {
                    "key": "field_5d1cf4b22aa2e",
                    "label": "Language Code",
                    "name": "lang",
                    "type": "text",
                    "instructions": "",
                    "required": 1,
                    "conditional_logic": 0,
                    "wrapper": {
                        "width": "35",
                        "class": "",
                        "id": ""
                    },
                    "default_value": "x-default",
                    "placeholder": "",
                    "prepend": "",
                    "append": "",
                    "maxlength": ""
                }
            ]
        }
    ],
    "location": [
        [
            {
                "param": "post_type",
                "operator": "==",
                "value": "page"
            }
        ]
    ],
    "menu_order": 99,
    "position": "normal",
    "style": "default",
    "label_placement": "top",
    "instruction_placement": "label",
    "hide_on_screen": [
        "the_content"
    ],
    "active": 1,
    "description": "",
    "modified": 1562945502
}